{
  "theme": "emotions",
  "language": "en",
  "words": [
    { "word": "JOY", "category": "positive", "difficulty": 1 },
    { "word": "LOVE", "category": "positive", "difficulty": 1 },
    { "word": "HOPE", "category": "positive", "difficulty": 1 },
    { "word": "CALM", "category": "positive", "difficulty": 1 },
    { "word": "GLAD", "category": "positive", "difficulty": 1 },
    { "word": "SAFE", "category": "positive", "difficulty": 1 },
    { "word": "WARM", "category": "positive", "difficulty": 1 },
    { "word": "FREE", "category": "positive", "difficulty": 1 },
    { "word": "BOLD", "category": "positive", "difficulty": 1 },
    { "word": "GLEE", "category": "positive", "difficulty": 1 },
    { "word": "FEAR", "category": "negative", "difficulty": 1 },
    { "word": "RAGE", "category": "negative", "difficulty": 1 },
    { "word": "PAIN", "category": "negative", "difficulty": 1 },
    { "word": "ENVY", "category": "negative", "difficulty": 1 },
    { "word": "DULL", "category": "neutral", "difficulty": 1 },
    { "word": "MILD", "category": "neutral", "difficulty": 1 },
    { "word": "NUMB", "category": "neutral", "difficulty": 1 },
    { "word": "TENSE", "category": "negative", "difficulty": 1 },
    { "word": "EAGER", "category": "positive", "difficulty": 1 },
    { "word": "PROUD", "category": "positive", "difficulty": 1 },
    { "word": "GRIEF", "category": "negative", "difficulty": 1 },
    { "word": "UPSET", "category": "negative", "difficulty": 1 },
    { "word": "TIRED", "category": "neutral", "difficulty": 1 },
    { "word": "BORED", "category": "neutral", "difficulty": 1 },
    { "word": "HAPPY", "category": "positive", "difficulty": 1 },
    { "word": "ANGRY", "category": "negative", "difficulty": 1 },
    { "word": "SORRY", "category": "neutral", "difficulty": 1 },
    { "word": "SHAME", "category": "negative", "difficulty": 1 },
    { "word": "SHOCK", "category": "neutral", "difficulty": 1 },
    { "word": "BLISS", "category": "positive", "difficulty": 1 },
    { "word": "GUILT", "category": "negative", "difficulty": 1 },
    { "word": "TRUST", "category": "positive", "difficulty": 1 },
    { "word": "DOUBT", "category": "negative", "difficulty": 1 },
    { "word": "DREAD", "category": "negative", "difficulty": 1 },
    { "word": "GREED", "category": "negative", "difficulty": 1 },
    { "word": "SCORN", "category": "negative", "difficulty": 1 },
    { "word": "PRIDE", "category": "positive", "difficulty": 1 },
    { "word": "GLOOM", "category": "negative", "difficulty": 1 },
    { "word": "PITY", "category": "neutral", "difficulty": 1 },
    { "word": "ENVY", "category": "negative", "difficulty": 1 },
    { "word": "RELIEF", "category": "positive", "difficulty": 2 },
    { "word": "SORROW", "category": "negative", "difficulty": 2 },
    { "word": "WONDER", "category": "positive", "difficulty": 2 },
    { "word": "FRIGHT", "category": "negative", "difficulty": 2 },
    { "word": "REGRET", "category": "negative", "difficulty": 2 },
    { "word": "HATRED", "category": "negative", "difficulty": 2 },
    { "word": "TENDER", "category": "positive", "difficulty": 2 },
    { "word": "ELATED", "category": "positive", "difficulty": 2 },
    { "word": "SERENE", "category": "positive", "difficulty": 2 },
    { "word": "JEALOUS", "category": "negative", "difficulty": 2 },
    { "word": "CONTENT", "category": "positive", "difficulty": 2 },
    { "word": "ANXIOUS", "category": "negative", "difficulty": 2 },
    { "word": "CURIOUS", "category": "positive", "difficulty": 2 },
    { "word": "HOPEFUL", "category": "positive", "difficulty": 2 },
    { "word": "EXCITED", "category": "positive", "difficulty": 2 },
    { "word": "NERVOUS", "category": "negative", "difficulty": 2 },
    { "word": "FURIOUS", "category": "negative", "difficulty": 2 },
    { "word": "DEVOTED", "category": "positive", "difficulty": 2 },
    { "word": "CHEERFUL", "category": "positive", "difficulty": 2 },
    { "word": "GRATEFUL", "category": "positive", "difficulty": 2 },
    { "word": "PEACEFUL", "category": "positive", "difficulty": 2 },
    { "word": "CONFUSED", "category": "neutral", "difficulty": 2 },
    { "word": "RESENTFUL", "category": "negative", "difficulty": 2 },
    { "word": "STRESSED", "category": "negative", "difficulty": 2 },
    { "word": "INSPIRED", "category": "positive", "difficulty": 2 },
    { "word": "ASHAMED", "category": "negative", "difficulty": 2 },
    { "word": "NERVOUS", "category": "negative", "difficulty": 2 },
    { "word": "ECSTATIC", "category": "positive", "difficulty": 2 },
    { "word": "ENVIOUS", "category": "negative", "difficulty": 2 },
    { "word": "RELAXED", "category": "positive", "difficulty": 2 },
    { "word": "YEARNING", "category": "neutral", "difficulty": 2 },
    { "word": "BITTERNESS", "category": "negative", "difficulty": 2 },
    { "word": "AFFECTION", "category": "positive", "difficulty": 2 },
    { "word": "NOSTALGIA", "category": "neutral", "difficulty": 2 },
    { "word": "MELANCHOLY", "category": "negative", "difficulty": 2 },
    { "word": "IRRITATED", "category": "negative", "difficulty": 2 },
    { "word": "FULFILLED", "category": "positive", "difficulty": 2 },
    { "word": "MOTIVATED", "category": "positive", "difficulty": 2 },
    { "word": "EMPATHY", "category": "positive", "difficulty": 2 },
    { "word": "HOMESICK", "category": "negative", "difficulty": 2 },
    { "word": "LONELINESS", "category": "negative", "difficulty": 3 },
    { "word": "COMPASSION", "category": "positive", "difficulty": 3 },
    { "word": "ADMIRATION", "category": "positive", "difficulty": 3 },
    { "word": "EXUBERANCE", "category": "positive", "difficulty": 3 },
    { "word": "IRRITATION", "category": "negative", "difficulty": 3 },
    { "word": "HEARTBREAK", "category": "negative", "difficulty": 3 },
    { "word": "WELLBEING", "category": "positive", "difficulty": 3 },
    { "word": "RESENTMENT", "category": "negative", "difficulty": 3 },
    { "word": "EAGERNESS", "category": "positive", "difficulty": 3 },
    { "word": "PERPLEXITY", "category": "neutral", "difficulty": 3 },
    { "word": "GRATITUDE", "category": "positive", "difficulty": 3 },
    { "word": "DESOLATION", "category": "negative", "difficulty": 3 },
    { "word": "MORTIFIED", "category": "negative", "difficulty": 3 },
    { "word": "OVERLOADED", "category": "negative", "difficulty": 3 },
    { "word": "DETACHMENT", "category": "neutral", "difficulty": 3 },
    { "word": "DISCOMFORT", "category": "negative", "difficulty": 3 },
    { "word": "ENTHUSIASM", "category": "positive", "difficulty": 3 },
    { "word": "TENDERNESS", "category": "positive", "difficulty": 3 },
    { "word": "DEPENDENCE", "category": "negative", "difficulty": 3 },
    { "word": "INSECURITY", "category": "neutral", "difficulty": 3 }
  ]
}
